{"cameraMode":{"drawMode":0,"name":"Shaded","section":"Shading Mode"},"sceneLighting":false,"audioPlay":false,"sceneViewState":{"m_AlwaysRefresh":false,"showFog":true,"showSkybox":false,"showFlares":true,"showImageEffects":true,"showParticleSystems":true,"showVisualEffectGraphs":true,"m_FxEnabled":true},"in2DMode":false,"pivot":{"x":-14.80685806274414,"y":14.77376937866211,"z":9.621213912963868},"rotation":{"x":-0.14801613986492158,"y":0.8331473469734192,"z":-0.2676236033439636,"w":-0.4607907831668854},"size":9.921587944030762,"orthographic":false}